{
  "https://suumo.jp/chukoikkodate/shizuoka/sc_suntogun/nc_20424710/|上長窪（長泉なめり駅） 3980万円": {
    "first_seen": "2026-06-17",
    "last_seen": "2026-06-22",
    "location": "静岡県駿東郡長泉町上長窪",
    "price_man": 3980,
    "area_sqm": 203.6,
    "url": "https://suumo.jp/chukoikkodate/shizuoka/sc_suntogun/nc_20424710/",
    "text": "上長窪（長泉なめり駅） 3980万円",
    "removed_on": "2026-06-22",
    "site_name": "SUUMO 中古戸建 駿東郡（清水/長泉）"
  },
  "https://suumo.jp/chukoikkodate/shizuoka/sc_suntogun/nc_21129679/|広い敷地で叶える落ち着きある和の暮らし": {
    "first_seen": "2026-06-22",
    "last_seen": "2026-06-23",
    "location": "静岡県駿東郡清水町柿田",
    "price_man": 2400,
    "area_sqm": 268.0,
    "url": "https://suumo.jp/chukoikkodate/shizuoka/sc_suntogun/nc_21129679/",
    "text": "広い敷地で叶える落ち着きある和の暮らし",
    "removed_on": "2026-06-23",
    "site_name": "SUUMO 中古戸建 駿東郡（清水/長泉）"
  },
  "https://suumo.jp/chukoikkodate/shizuoka/sc_suntogun/nc_76264260/|下土狩（三島駅） 1250万円": {
    "first_seen": "2026-06-17",
    "last_seen": "2026-06-24",
    "location": "静岡県駿東郡長泉町下土狩",
    "price_man": 1250,
    "area_sqm": 77.3,
    "url": "https://suumo.jp/chukoikkodate/shizuoka/sc_suntogun/nc_76264260/",
    "text": "下土狩（三島駅） 1250万円",
    "removed_on": "2026-06-25",
    "site_name": "SUUMO 中古戸建 駿東郡（清水/長泉）"
  },
  "https://suumo.jp/chukoikkodate/shizuoka/sc_suntogun/nc_20667797/|自然豊かなスルガ平の物件！歴史と文化、自然の魅力に満ちた街並み敷地面積約": {
    "first_seen": "2026-06-22",
    "last_seen": "2026-06-25",
    "location": "静岡県駿東郡長泉町東野",
    "price_man": 1999,
    "area_sqm": 299.0,
    "url": "https://suumo.jp/chukoikkodate/shizuoka/sc_suntogun/nc_20667797/",
    "text": "自然豊かなスルガ平の物件！歴史と文化、自然の魅力に満ちた街並み敷地面積約",
    "removed_on": "2026-06-26",
    "site_name": "SUUMO 中古戸建 駿東郡（清水/長泉）"
  },
  "https://suumo.jp/chukoikkodate/shizuoka/sc_suntogun/nc_20966371/|土地：約２５２坪、建物：約４８坪！暖かい日差したっぷりの穏やかな住環境！": {
    "first_seen": "2026-06-25",
    "last_seen": "2026-06-25",
    "location": "静岡県駿東郡長泉町東野515-122",
    "price_man": 2780,
    "area_sqm": 835.8,
    "url": "https://suumo.jp/chukoikkodate/shizuoka/sc_suntogun/nc_20966371/",
    "text": "土地：約２５２坪、建物：約４８坪！暖かい日差したっぷりの穏やかな住環境！",
    "removed_on": "2026-06-26",
    "site_name": "SUUMO 中古戸建 駿東郡（清水/長泉）"
  },
  "https://suumo.jp/chukoikkodate/shizuoka/sc_suntogun/nc_77869077/|☆　敷地面積600坪と広々しています。　　→工場と住宅が併設しています。": {
    "first_seen": "2026-06-17",
    "last_seen": "2026-06-25",
    "location": "静岡県駿東郡長泉町下長窪",
    "price_man": 24000,
    "area_sqm": 2000.2,
    "url": "https://suumo.jp/chukoikkodate/shizuoka/sc_suntogun/nc_77869077/",
    "text": "☆　敷地面積600坪と広々しています。　　→工場と住宅が併設しています。",
    "removed_on": "2026-06-26",
    "site_name": "SUUMO 中古戸建 駿東郡（清水/長泉）"
  },
  "https://suumo.jp/chukoikkodate/shizuoka/sc_suntogun/nc_79156787/|元長窪（長泉なめり駅） 1760万円": {
    "first_seen": "2026-06-17",
    "last_seen": "2026-06-26",
    "location": "静岡県駿東郡長泉町元長窪",
    "price_man": 1760,
    "area_sqm": 163.0,
    "url": "https://suumo.jp/chukoikkodate/shizuoka/sc_suntogun/nc_79156787/",
    "text": "元長窪（長泉なめり駅） 1760万円",
    "removed_on": "2026-06-27",
    "site_name": "SUUMO 中古戸建 駿東郡（清水/長泉）"
  }
}